area_forecast_discussion/__init__.py
area_forecast_discussion/generate_afd_url.py
area_forecast_discussion/get_afd_for_location.py
area_forecast_discussion/get_forecast_office.py
area_forecast_discussion/parse_afd_html.py
area_forecast_discussion/requirements.txt
area_forecast_discussion-0.1.0.dist-info/METADATA
area_forecast_discussion-0.1.0.dist-info/WHEEL
area_forecast_discussion-0.1.0.dist-info/RECORD
