Metadata-Version: 2.4
Name: area-forecast-discussion
Version: 0.1.0
Summary: Python package to gather, parse, and present Area Forecast Discussions for regions in the U.S.
Author-email: Derrick Day <brlkid@outlook.com>
Requires-Python: >=3.12
Requires-Dist: requests>=2.32.5
